_libxeddsa.pypy310-pp73-darwin.so
xeddsa/version.py
xeddsa/libxeddsa_emscripten.py
xeddsa/__init__.py
xeddsa/bindings.py
xeddsa/py.typed
xeddsa-1.2.0.dist-info/RECORD
xeddsa-1.2.0.dist-info/WHEEL
xeddsa-1.2.0.dist-info/top_level.txt
xeddsa-1.2.0.dist-info/METADATA
xeddsa-1.2.0.dist-info/licenses/LICENSE
