Metadata-Version: 2.4
Name: XEdDSA
Version: 1.2.0
Summary: Python bindings to libxeddsa.
Author-email: "Tim Henkes (Syndace)" <me@syndace.dev>
Maintainer-email: "Tim Henkes (Syndace)" <me@syndace.dev>
License-Expression: MIT
Project-URL: Documentation, https://python-xeddsa.readthedocs.io/
Project-URL: Repository, https://github.com/Syndace/python-xeddsa
Project-URL: Issues, https://github.com/Syndace/python-xeddsa/issues
Project-URL: Changelog, https://github.com/Syndace/python-xeddsa/blob/main/CHANGELOG.md
Classifier: Development Status :: 5 - Production/Stable
Classifier: Programming Language :: Python :: 3
Classifier: Programming Language :: Python :: 3 :: Only
Classifier: Programming Language :: Python :: 3.10
Classifier: Programming Language :: Python :: 3.11
Classifier: Programming Language :: Python :: 3.12
Classifier: Programming Language :: Python :: 3.13
Classifier: Programming Language :: Python :: 3.14
Classifier: Programming Language :: Python :: Implementation :: CPython
Classifier: Programming Language :: Python :: Implementation :: PyPy
Classifier: Intended Audience :: Developers
Classifier: Topic :: Security :: Cryptography
Requires-Python: >=3.10
License-File: LICENSE
Requires-Dist: cffi>=1.14.5
Provides-Extra: docs
Requires-Dist: sphinx; extra == "docs"
Requires-Dist: sphinx-rtd-theme; extra == "docs"
Requires-Dist: sphinx-autodoc-typehints; extra == "docs"
Provides-Extra: test
Requires-Dist: pytest; extra == "test"
Requires-Dist: pytest-cov; extra == "test"
Provides-Extra: lint
Requires-Dist: mypy; extra == "lint"
Requires-Dist: types-cffi; extra == "lint"
Requires-Dist: types-setuptools; extra == "lint"
Requires-Dist: pylint; extra == "lint"
Requires-Dist: setuptools; extra == "lint"
Requires-Dist: flake8; extra == "lint"
Requires-Dist: flake8-pyproject; extra == "lint"
Provides-Extra: dev
Requires-Dist: xeddsa[docs,lint,test]; extra == "dev"
Dynamic: license-file
